HISTORY.md
paraloq/__init__.py
paraloq/installer/__init__.py
paraloq/installer/cli.py
paraloq/installer/exceptions.py
paraloq/installer/login.py
paraloq/installer/prompt.py
paraloq/installer/server.py
paraloq/installer/session.py
paraloq_installer_experimental-0.1.3.dist-info/entry_points.txt
paraloq_installer_experimental-0.1.3.dist-info/WHEEL
paraloq_installer_experimental-0.1.3.dist-info/METADATA
paraloq_installer_experimental-0.1.3.dist-info/RECORD
